twikidata/__main__.py
twikidata/models.py
twikidata-0.2.14.dist-info/entry_points.txt
twikidata-0.2.14.dist-info/WHEEL
twikidata-0.2.14.dist-info/METADATA
twikidata-0.2.14.dist-info/RECORD
